usermgr/Factory.py
usermgr/__init__.py
usermgr/base.py
usermgr/providers/__init__.py
usermgr/providers/cognito.py
usermgr/providers/lambda.py
usermgr-0.3.1.dist-info/LICENSE
usermgr-0.3.1.dist-info/METADATA
usermgr-0.3.1.dist-info/WHEEL
usermgr-0.3.1.dist-info/RECORD
