Metadata-Version: 2.1
Name: usermgr
Version: 0.3.1
Summary: 
Home-page: https://github.com/tamuto/usermgr
Author: tamuto
Author-email: tamuto@infodb.jp
Requires-Python: >=3.9,<4.0
Classifier: Programming Language :: Python :: 3
Classifier: Programming Language :: Python :: 3.9
Classifier: Programming Language :: Python :: 3.10
Classifier: Programming Language :: Python :: 3.11
Provides-Extra: cognito
Provides-Extra: lambda
Requires-Dist: boto3 (>=1.26.54,<2.0.0) ; extra == "cognito" or extra == "lambda"
Project-URL: Repository, https://github.com/tamuto/usermgr
